guish/__init__.py
guish/guish.py
guish-0.0.1.dev1.dist-info/LICENSE
guish-0.0.1.dev1.dist-info/METADATA
guish-0.0.1.dev1.dist-info/WHEEL
guish-0.0.1.dev1.dist-info/top_level.txt
guish-0.0.1.dev1.dist-info/RECORD
