Metadata-Version: 2.1
Name: guish
Version: 0.0.1.dev1
Summary: A simple GUI.
Author-email: Nick Stuer <nickstuer@duck.com>
Project-URL: Homepage, https://github.com/nickstuer/guish
Project-URL: Issues, https://github.com/nickstuer/guish/issues
Classifier: Programming Language :: Python :: 3
Classifier: License :: OSI Approved :: MIT License
Classifier: Operating System :: OS Independent
Requires-Python: >=3.8
License-File: LICENSE
